{"cameraMode":{"drawMode":0,"name":"Shaded","section":"Shading Mode"},"sceneLighting":true,"audioPlay":false,"sceneViewState":{"m_AlwaysRefresh":false,"showFog":true,"showSkybox":true,"showFlares":true,"showImageEffects":true,"showParticleSystems":true,"showVisualEffectGraphs":true,"m_FxEnabled":true},"in2DMode":false,"pivot":{"x":-19.432382583618165,"y":9.274856567382813,"z":-5.875946044921875},"rotation":{"x":0.46112433075904848,"y":0.5372350811958313,"z":-0.4700642228126526,"w":0.527023434638977},"size":19.476245880126954,"orthographic":false}